porringer-0.1.0.dist-info/METADATA
porringer-0.1.0.dist-info/WHEEL
porringer-0.1.0.dist-info/entry_points.txt
porringer-0.1.0.dist-info/licenses/LICENSE.md
porringer/__init__.py
porringer/api.py
porringer/backend/__init__.py
porringer/backend/builder.py
porringer/backend/command/__init__.py
porringer/backend/command/plugin.py
porringer/backend/command/self.py
porringer/backend/command/version.py
porringer/backend/resolver.py
porringer/backend/schema.py
porringer/console/__init__.py
porringer/console/command/__init__.py
porringer/console/command/plugin.py
porringer/console/command/self.py
porringer/console/entry.py
porringer/console/schema.py
porringer/core/__init__.py
porringer/core/plugin_schema/__init__.py
porringer/core/plugin_schema/environment.py
porringer/core/schema.py
porringer/plugin/__init__.py
porringer/plugin/pip/__init__.py
porringer/plugin/pip/plugin.py
porringer/plugin/pipx/__init__.py
porringer/plugin/pipx/plugin.py
porringer/plugin/winget/__init__.py
porringer/plugin/winget/plugin.py
porringer/py.typed
porringer/schema.py
porringer/test/mock/__init__.py
porringer/test/mock/environment.py
porringer/test/pytest/__init__.py
porringer/test/pytest/plugin.py
porringer/test/pytest/shared.py
porringer/test/pytest/tests.py
porringer/test/pytest/variants.py
porringer/utility/__init__.py
porringer/utility/exception.py
porringer/utility/plugin.py
porringer/utility/py.typed
porringer/utility/utility.py
porringer-0.1.0.dist-info/RECORD
