Metadata-Version: 2.1
Name: porringer
Version: 0.1.0
Author-Email: Synodic Software <contact@synodic.software>
License: MIT
Project-URL: homepage, https://github.com/Synodic-Software/Porringer
Project-URL: repository, https://github.com/Synodic-Software/Porringer
Requires-Python: >=3.13
Requires-Dist: typer[all]>=0.15.2
Requires-Dist: pydantic>=2.11.3
Requires-Dist: platformdirs>=4.3.7
Requires-Dist: userpath>=1.9.2
Requires-Dist: packaging>=24.2
